fastboost/__init__.py
fastboost/__init__old.py
fastboost/__main__.py
fastboost/constant.py
fastboost/funboost_config_deafult.py
fastboost/set_frame_config.py
fastboost/assist/__init__.py
fastboost/assist/celery_helper.py
fastboost/assist/dramatiq_helper.py
fastboost/assist/faststream_helper.py
fastboost/assist/huey_helper.py
fastboost/assist/rocketry_helper.py
fastboost/assist/rq_helper.py
fastboost/assist/rq_windows_worker.py
fastboost/assist/taskiq_helper.py
fastboost/beggar_version_implementation/beggar_redis_consumer.py
fastboost/concurrent_pool/__init__.py
fastboost/concurrent_pool/async_helper.py
fastboost/concurrent_pool/async_pool_executor.py
fastboost/concurrent_pool/base_pool_type.py
fastboost/concurrent_pool/bounded_processpoolexcutor_gt_py37.py
fastboost/concurrent_pool/bounded_processpoolexcutor_py36.py
fastboost/concurrent_pool/bounded_threadpoolexcutor.py
fastboost/concurrent_pool/concurrent_pool_with_multi_process.py
fastboost/concurrent_pool/custom_evenlet_pool_executor.py
fastboost/concurrent_pool/custom_gevent_pool_executor.py
fastboost/concurrent_pool/custom_threadpool_executor.py
fastboost/concurrent_pool/custom_threadpool_executor000.py
fastboost/concurrent_pool/fixed_thread_pool.py
fastboost/concurrent_pool/flexible_thread_pool.py
fastboost/concurrent_pool/pool_commons.py
fastboost/concurrent_pool/single_thread_executor.py
fastboost/concurrent_pool/backup/__init__.py
fastboost/concurrent_pool/backup/async_pool_executor0223.py
fastboost/concurrent_pool/backup/async_pool_executor_back.py
fastboost/concurrent_pool/backup/async_pool_executor_janus.py
fastboost/concurrent_pool/backup/grok_async_pool.py
fastboost/consumers/__init__.py
fastboost/consumers/ailiyun_rocketmq_consumer.py
fastboost/consumers/base_consumer.py
fastboost/consumers/celery_consumer.py
fastboost/consumers/confirm_mixin.py
fastboost/consumers/dramatiq_consumer.py
fastboost/consumers/empty_consumer.py
fastboost/consumers/faststream_consumer.py
fastboost-1.1.91.dist-info/LICENSE
fastboost-1.1.91.dist-info/METADATA
fastboost-1.1.91.dist-info/WHEEL
fastboost-1.1.91.dist-info/entry_points.txt
fastboost-1.1.91.dist-info/top_level.txt
fastboost-1.1.91.dist-info/RECORD
