Metadata-Version: 2.1
Name: fastboost
Version: 1.1.91
Summary: pip install fastboost，python全功能分布式函数调度框架,fastboost的功能是全面性重量级，用户能想得到的功能99%全都有;fastboost的使用方式是轻量级，只有@boost一行代码需要写。支持python所有类型的并发模式和一切知名消息队列中间件，支持如 celery dramatiq等框架整体作为fastboost中间件，python函数加速器，框架包罗万象，用户能想到的控制功能全都有。一统编程思维，兼容50% python业务场景，适用范围广。只需要一行代码即可分布式执行python一切函数，99%用过fastboost的pythoner 感受是　简易 方便 强劲 强大，相见恨晚 
Home-page: 
Author: 
Author-email: 
Maintainer: 
Maintainer-email: 
License: BSD License
Keywords: fastboost,distributed-framework,function-scheduling,rabbitmq,rocketmq,kafka,nsq,redis,disk,sqlachemy,consume-confirm,timing,task-scheduling,apscheduler,pulsar,mqtt,kombu,的,celery,框架,分布式调度
Platform: all
Classifier: Development Status :: 4 - Beta
Classifier: Operating System :: OS Independent
Classifier: Intended Audience :: Developers
Classifier: License :: OSI Approved :: BSD License
Classifier: Programming Language :: Python
Classifier: Programming Language :: Python :: Implementation
Classifier: Programming Language :: Python :: 3
Classifier: Programming Language :: Python :: 3.7
Classifier: Programming Language :: Python :: 3.8
Classifier: Programming Language :: Python :: 3.9
Classifier: Programming Language :: Python :: 3.10
Classifier: Programming Language :: Python :: 3.11
Classifier: Programming Language :: Python :: 3.12
Classifier: Topic :: Software Development :: Libraries
License-File: LICENSE
Requires-Dist: nb-log >=12.6
Requires-Dist: nb-libs >=1.8
Requires-Dist: nb-time >=1.8
Requires-Dist: pymongo ==3.5.1
Requires-Dist: AMQPStorm ==2.10.6
Requires-Dist: decorator ==4.1.1
Requires-Dist: tomorrow3 ==1.1.0
Requires-Dist: apscheduler ==3.10.1
Requires-Dist: twisted ==21.7.0
Requires-Dist: pikav0
Requires-Dist: pikav1
Requires-Dist: redis2
Requires-Dist: redis3
Requires-Dist: redis55 ==1.0.3
Requires-Dist: redis ==3.5.1
Requires-Dist: setuptools-rust
Requires-Dist: fabric2 ==2.6.0
Requires-Dist: nb-filelock
Requires-Dist: pysnooper
Requires-Dist: deprecated
Requires-Dist: cryptography
Requires-Dist: auto-run-on-remote
Requires-Dist: frozenlist
Requires-Dist: fire
Requires-Dist: pydantic
Requires-Dist: orjson
Requires-Dist: rocketmq ==0.4.4
Requires-Dist: rocketmq-client ==0.1.0
Requires-Dist: alibabacloud-rocketmq20220801 ==3.1.1
Provides-Extra: all
Requires-Dist: sqlalchemy ==1.4.13 ; extra == 'all'
Requires-Dist: sqlalchemy-utils ==0.36.1 ; extra == 'all'
Requires-Dist: eventlet ==0.33.3 ; extra == 'all'
Requires-Dist: gevent ==22.10.2 ; extra == 'all'
Requires-Dist: psutil ; extra == 'all'
Requires-Dist: nats-python ; extra == 'all'
Provides-Extra: extra_brokers
Requires-Dist: sqlalchemy ==1.4.13 ; extra == 'extra_brokers'
Requires-Dist: sqlalchemy-utils ==0.36.1 ; extra == 'extra_brokers'
Requires-Dist: eventlet ==0.33.3 ; extra == 'extra_brokers'
Requires-Dist: gevent ==22.10.2 ; extra == 'extra_brokers'
Requires-Dist: psutil ; extra == 'extra_brokers'
Requires-Dist: nats-python ; extra == 'extra_brokers'
Provides-Extra: flask
